{"guide_changelog_v1.2.1.md":"5aKxWJlh","guide_develop_on_linux.md":"XmsPyVkV","guide_changelog_v1.1.6.md":"FX8KW7DZ","guide_changelog_v1.2.5.md":"a_3Aeoxu","guide_changelog_v1.2.0.md":"1KPSTsIK","guide_changelog_v1.2.3.md":"e1N_U3pn","guide_changelog_v1.2.4.md":"X0x40sH0","guide_develop_on_windows.md":"qRGdB21H","guide_changelog_v1.2.2.md":"tUfCY3Ff","guide_contact.md":"AShINOJC","readme.md":"069F3koB","guide_feature.md":"BxvtYyAJ","guide_changelog_v1.1.5.md":"R5mxkhC7","guide_changelog_v1.1.4.md":"JJDhGLy3","guide_changelog_v1.1.3.md":"zsRvMCLY","guide_format.md":"0k_UyBei","zh_guide_plugin_binary_gs.md":"jdRqXKuh","zh_guide_feature.md":"2BcFnyVt","zh_guide_plugin_binary_inkscape.md":"2W6dhPHL","zh_guide_plugin_binary_rsvg_convert.md":"0GON1wBk","zh_guide_plugin_data_pdf.md":"rltTLMD4","guide_plugin_binary_rsvg_convert.md":"NYF0c78d","zh_guide_plugin_binary.md":"jYdS_j0m","zh_guide_what-is-mogan.md":"UDy7USvg","zh_guide_plugin_image_pdf.md":"bZYfQ2kR","zh_guide_git.md":"GP4LVkuH","zh_guide_plugin_image_svg.md":"FfAjmwO8","zh_guide_mogan_versus_texmacs.md":"5sfwpQfG","zh_guide_install.md":"jLn98qnJ","guide_plugin_binary_python3.md":"5AYJ2QQ6","zh_guide_changelog_v1.1.6.md":"cK-esPv5","guide_plugin_data_pdf.md":"4m_9-YvR","zh_guide_plugin_binary_python3.md":"n-TDWK4_","guide_plugin_image_svg.md":"xHbH0B6X","guide_plugin_session_maxima.md":"D6sv-xwR","guide_plugin_session_octave.md":"JnDxZBfd","zh_guide_develop_on_macos.md":"WY2RCheN","zh_guide_changelog_v1.2.0.md":"ujIn-ea_","zh_guide_changelog_v1.2.1.md":"mIVLX6ts","guide_install.md":"aYaLkniI","guide_git.md":"ucJLbcwp","guide_test.md":"ZSLtoW7W","index.md":"fVItM7Wa","guide_plugin_binary.md":"gQ-G_tuk","zh_guide_changelog_v1.0.0.md":"QS7hPJ4C","guide_plugin_binary_inkscape.md":"4ICplvQu","guide_plugin_binary_gs.md":"EfKAV1SI","zh_guide_changelog_v1.0.1.md":"eGjtQ8H2","zh_guide_changelog_v1.0.2.md":"5jltynTS","zh_guide_changelog_v1.0.3.md":"g6SfxKMY","zh_guide_changelog_v1.0.4.md":"xiL8tiM8","zh_guide_changelog_v1.1.1.md":"HLLw_lXI","zh_guide_changelog_v1.1.2.md":"jlsZDWYK","zh_guide_changelog_v1.1.0.md":"Rr9mHvnw","guide_plugins.md":"xBJffRGW","zh_guide_changelog_v1.2.2.md":"bHO2JB6m","guide_contribution.md":"b-1V3DiR","zh_guide_changelog_v1.1.4.md":"mT9Hcpdl","zh_guide_changelog_v1.2.3.md":"jEK5bD8m","zh_guide_changelog_v1.2.4.md":"fqvQwdL8","guide_mogan_versus_texmacs.md":"D0Rv3yMA","zh_guide_changelog_v1.2.5.md":"3buUhSC_","zh_guide_contact.md":"lKBigmLf","zh_guide_contribution.md":"BhWJMLeL","zh_guide_develop_on_linux.md":"xjGAV7XW","zh_guide_format.md":"WVpEGd7S","zh_guide_develop_on_windows.md":"d7Rv1aGX","zh_guide_plugin_session_maxima.md":"nEBzB7vq","guide_plugin_image_pdf.md":"Bs3DPuMV","zh_guide_plugins.md":"SKmEn-ux","guide_develop_on_macos.md":"5v5gNgOa","zh_guide_test.md":"Bksd5Dys","zh_guide_plugin_session_octave.md":"wiHME7fA","guide_what-is-mogan.md":"Zod7bfsi","zh_guide_changelog_v1.1.5.md":"a3S3FF7o","zh_guide_changelog_v1.1.3.md":"rhYLpq2y"}
